nr_generic/__init__.py
nr_generic/config.py
nr_generic/constants.py
nr_generic/ext.py
nr_generic/fetchers.py
nr_generic/mappings/__init__.py
nr_generic/mappings/v7/__init__.py
nr_generic/mappings/v7/nr_common/nr-common-v1.0.0.json
nr_generic/minters.py
nr_generic/providers.py
nr_generic/record.py
nr_generic/search.py
techlib_nr_generic-1.0.0a7.dist-info/entry_points.txt
techlib_nr_generic-1.0.0a7.dist-info/WHEEL
techlib_nr_generic-1.0.0a7.dist-info/METADATA
techlib_nr_generic-1.0.0a7.dist-info/RECORD
