Metadata-Version: 2.1
Name: techlib-nr-generic
Version: 1.0.0a7
Summary: NR generic model REST API
License: MIT
Keywords: National,Repository,common,model,Invenio
Author: Mirek Simek
Author-email: simeki@vscht.cz
Requires-Python: >=3.8,<4.0
Classifier: Development Status :: 3 - Alpha
Classifier: Environment :: Web Environment
Classifier: Intended Audience :: Developers
Classifier: License :: OSI Approved :: MIT License
Classifier: Operating System :: OS Independent
Classifier: Programming Language :: Python
Classifier: Programming Language :: Python :: 3
Classifier: Programming Language :: Python :: 3.8
Classifier: Programming Language :: Python :: 3.9
Classifier: Topic :: Internet :: WWW/HTTP :: Dynamic Content
Classifier: Topic :: Software Development :: Libraries :: Python Modules
Provides-Extra: docs
Requires-Dist: idutils (>=1.1.8,<2.0.0)
Requires-Dist: isbnlib (>=3.10.3,<4.0.0)
Requires-Dist: oarepo-invenio-model (>=2.0.0,<3.0.0)
Requires-Dist: python-stdnum (>=1.16,<2.0)
Requires-Dist: sphinx (>=1.5.1,<2.0.0); extra == "docs"
Requires-Dist: techlib-nr-common (>=3.0.0a45,<4.0.0)
